[
    {
        "rhyme_amount_by_para": [
            5,
            5
        ],
        "rhyme_hanzi": [
            "韵",
            "韵",
            "韵",
            "韵",
            "韵",
            "韵",
            "韵",
            "韵",
            "韵",
            "韵"
        ],
        "rhyme_pos_by_para": [
            [
                9,
                19,
                29,
                35,
                44
            ],
            [
                54,
                64,
                74,
                80,
                89
            ]
        ],
        "ge_lyu_str": "中平平仄平中仄平平仄中仄仄平平中仄平平仄中仄平平仄平仄平平仄仄平平平仄仄仄平平仄平仄平平仄平平仄仄平仄仄平平仄仄仄中平中中仄平平仄仄仄平平仄中仄平平仄平中仄平仄仄中平中仄平仄平平仄",
        "rhyme_pos": [
            9,
            19,
            29,
            35,
            44,
            54,
            64,
            74,
            80,
            89
        ],
        "yun_classify": {
            "0": [
                9,
                19,
                29,
                35,
                44,
                54,
                64,
                74,
                80,
                89
            ]
        },
        "ci_sep": [
            "缭墙重院　时闻有　流莺到",
            "绣被掩馀寒　画阁明新晓",
            "朱槛连空阔　飞絮无多少",
            "径莎平　池水渺",
            "日长风静　花影閒相照",
            "尘香拂马　逢谢女　城南道",
            "秀艳过施粉　多媚生轻笑",
            "斗色鲜衣薄　碾玉双蝉小",
            "欢难偶　春过了",
            "琵琶流韵　都入相思调"
        ],
        "ge_lyu_sep": [
            "中平平仄句平中仄读平平仄韵",
            "中仄仄平平句中仄平平仄韵",
            "中仄平平仄句平仄平平仄韵",
            "仄平平句平仄仄韵",
            "仄平平仄句平仄平平仄韵",
            "平平仄仄句平仄仄读平平仄韵",
            "仄仄中平中句中仄平平仄韵",
            "仄仄平平仄句中仄平平仄韵",
            "平中仄句平仄仄韵",
            "中平中仄句平仄平平仄韵"
        ]
    }
]