[
    {
        "rhyme_amount_by_para": [
            3,
            3
        ],
        "rhyme_hanzi": [
            "韵",
            "韵",
            "韵",
            "韵",
            "韵",
            "韵"
        ],
        "rhyme_pos_by_para": [
            [
                6,
                13,
                27
            ],
            [
                34,
                41,
                55
            ]
        ],
        "ge_lyu_str": "仄仄平平平仄仄仄仄仄平平平仄平仄仄平仄仄平平平仄仄平平仄平平仄仄平平仄仄平平仄平平仄仄仄仄平仄仄平平平仄仄平平仄",
        "rhyme_pos": [
            6,
            13,
            27,
            34,
            41,
            55
        ],
        "yun_classify": {
            "0": [
                6,
                13,
                27,
                34,
                41,
                55
            ]
        },
        "ci_sep": [
            "镂玉香葩酥点萼",
            "正万木　园林萧索",
            "惟有一枝雪里开　江南信　更凭谁托",
            "前年记赏登高阁",
            "叹年来　旧欢如昨",
            "听取乐天一句云　花开处　且须行乐"
        ],
        "ge_lyu_sep": [
            "仄仄平平平仄仄韵",
            "仄仄仄读平平平仄韵",
            "平仄仄平仄仄平句平平仄读仄平平仄韵",
            "平平仄仄平平仄韵",
            "仄平平读仄平平仄韵",
            "仄仄仄平仄仄平句平平仄读仄平平仄韵"
        ]
    }
]