[
    {
        "rhyme_amount_by_para": [
            4,
            7
        ],
        "rhyme_hanzi": [
            "韵",
            "韵",
            "韵",
            "韵",
            "韵",
            "韵",
            "韵",
            "韵",
            "韵",
            "韵",
            "韵"
        ],
        "rhyme_pos_by_para": [
            [
                12,
                22,
                27,
                48
            ],
            [
                51,
                54,
                59,
                62,
                70,
                75,
                96
            ]
        ],
        "ge_lyu_str": "仄仄平仄仄平平平仄平平仄仄仄仄仄平平仄仄平平仄仄仄平平仄仄平平仄仄平平仄仄仄平仄仄平平平平仄仄平仄平仄仄平平仄仄仄仄平仄平仄仄仄仄仄平仄平平仄平仄平平仄仄平平仄仄平平仄仄仄平仄仄平平平仄仄平平仄",
        "rhyme_pos": [
            12,
            22,
            27,
            48,
            51,
            54,
            59,
            62,
            70,
            75,
            96
        ],
        "yun_classify": {
            "0": [
                12,
                22,
                27,
                48,
                51,
                54,
                59,
                62,
                70,
                75,
                96
            ]
        },
        "ci_sep": [
            "雨乍收　小院尘消　云淡天高露冷",
            "坐看月华生　射玉楼清莹",
            "蟋蟀鸣金井",
            "下帘帏　悄悄空阶　败叶坠风　惹动閒愁　千端万绪难整",
            "秋夜永",
            "凉天迥",
            "可不念光景",
            "嗟薄命",
            "倏忽少年　忍教孤另",
            "灯闪红窗影",
            "步回廊　懒入香闺　暗落泪珠满面　谁人知我　为伊成病"
        ],
        "ge_lyu_sep": [
            "仄仄平读仄仄平平句平仄平平仄仄韵",
            "仄仄仄平平句仄仄平平仄韵",
            "仄仄平平仄韵",
            "仄平平读仄仄平平句仄仄仄平句仄仄平平句平平仄仄平仄韵",
            "平仄仄韵",
            "平平仄韵",
            "仄仄仄平仄韵",
            "平仄仄韵",
            "仄仄仄平句仄平平仄韵",
            "平仄平平仄韵",
            "仄平平读仄仄平平句仄仄仄平仄仄句平平平仄句仄平平仄韵"
        ]
    }
]